emotionlinmult/__init__.py
emotionlinmult/preprocess/afewva_info.py
emotionlinmult/preprocess/afewva_visual.py
emotionlinmult/preprocess/affwild2_visual.py
emotionlinmult/preprocess/celebvhq_info.py
emotionlinmult/preprocess/celebvhq_visual.py
emotionlinmult/preprocess/cremad_visual.py
emotionlinmult/preprocess/mead_acoustic.py
emotionlinmult/preprocess/mead_visual.py
emotionlinmult/preprocess/meld_visual.py
emotionlinmult/preprocess/ravdess_acoustic.py
emotionlinmult/preprocess/ravdess_info.py
emotionlinmult/preprocess/ravdess_visual.py
emotionlinmult/preprocess/old/old_audio.py
emotionlinmult/preprocess/old/old_mead_audio.py
emotionlinmult/preprocess/old/old_mead_extract_all.py
emotionlinmult/preprocess/old/old_mead_text.py
emotionlinmult-0.1.0.dist-info/METADATA
emotionlinmult-0.1.0.dist-info/WHEEL
emotionlinmult-0.1.0.dist-info/licenses/LICENSE
emotionlinmult-0.1.0.dist-info/RECORD
