Metadata-Version: 2.4
Name: emotionlinmult
Version: 0.1.0
Summary: EmotionLinMulT: Transformer-based Emotion Recognition and Estimation.
Project-URL: Documentation, https://github.com/fodorad/emotionlinmult#readme
Project-URL: Issues, https://github.com/fodorad/emotionlinmult/issues
Project-URL: Source, https://github.com/fodorad/emotionlinmult
Author-email: fodorad <foauaai@inf.elte.hu>
License-Expression: MIT
License-File: LICENSE
Keywords: audio,emotion,intensity,multimodal,preprocess,text,video
Classifier: License :: OSI Approved :: MIT License
Classifier: Operating System :: OS Independent
Classifier: Programming Language :: Python :: 3
Requires-Python: >=3.11
Requires-Dist: decord
Requires-Dist: lightning
Requires-Dist: linmult
Requires-Dist: matplotlib
Requires-Dist: opencv-contrib-python
Requires-Dist: opencv-python
Requires-Dist: pillow
Requires-Dist: prettytable
Requires-Dist: pydub
Requires-Dist: pyyaml
Requires-Dist: scipy
Requires-Dist: seaborn
Requires-Dist: toml
Requires-Dist: torch==2.5.1
Requires-Dist: torchaudio==2.5.1
Requires-Dist: tqdm
Provides-Extra: dev
Requires-Dist: exordium; extra == 'dev'
Requires-Dist: matplotlib; extra == 'dev'
Requires-Dist: seaborn; extra == 'dev'
Requires-Dist: tqdm; extra == 'dev'
